bpf2eaf/BPFParser.py
bpf2eaf/ErrorCodesBPF2EAF.py
bpf2eaf/XML_Validation.py
bpf2eaf/__init__.py
bpf2eaf/bpf2eaf.py
bpf2eaf-0.0.5.dist-info/LICENSE
bpf2eaf-0.0.5.dist-info/METADATA
bpf2eaf-0.0.5.dist-info/WHEEL
bpf2eaf-0.0.5.dist-info/top_level.txt
bpf2eaf-0.0.5.dist-info/RECORD
