Metadata-Version: 2.1
Name: bpf2eaf
Version: 0.0.5
Summary: Package converting bpf to eaf.
Home-page: UNKNOWN
Author: Thomas Kisler
Author-email: kisler@bas.uni-muenchen.de
License: Copyright (c) 2019 Thomas Kisler
